servicex/__init__.py
servicex/_version.py
servicex/configuration.py
servicex/databinder_models.py
servicex/dataset_group.py
servicex/dataset_identifier.py
servicex/expandable_progress.py
servicex/minio_adapter.py
servicex/models.py
servicex/python_dataset.py
servicex/query_cache.py
servicex/query_core.py
servicex/servicex_adapter.py
servicex/servicex_client.py
servicex/types.py
servicex/app/__init__.py
servicex/app/cache.py
servicex/app/cli_options.py
servicex/app/codegen.py
servicex/app/datasets.py
servicex/app/init.py
servicex/app/main.py
servicex/app/transforms.py
servicex/dataset/__init__.py
servicex/func_adl/__init__.py
servicex/func_adl/func_adl_dataset.py
servicex/query/__init__.py
servicex/topcp/topcp.py
servicex/uproot_raw/uproot_raw.py
servicex/yaml_parser/__init__.py
servicex/yaml_parser/parser.py
servicex-3.3.0.dist-info/METADATA
servicex-3.3.0.dist-info/WHEEL
servicex-3.3.0.dist-info/entry_points.txt
servicex-3.3.0.dist-info/licenses/LICENSE
servicex-3.3.0.dist-info/RECORD
